streamlitopencvideoplayer/__init__.py
streamlitopencvideoplayer/app.py
streamlitopencvplayer/__init__.py
streamlitopencvplayer/app.py
test/__init__.py
test/test.py
streamlitopencvideoplayer-1.0.0.dist-info/METADATA
streamlitopencvideoplayer-1.0.0.dist-info/WHEEL
streamlitopencvideoplayer-1.0.0.dist-info/top_level.txt
streamlitopencvideoplayer-1.0.0.dist-info/RECORD
