Metadata-Version: 2.1
Name: streamlitopencvideoplayer
Version: 1.0.0
Summary: Streamlit Opencv player
Author: Nafaa Bougraine
Author-email: bougraine.nafaa@gmail.com
Keywords: python,package
Classifier: Programming Language :: Python :: 3
Classifier: Operating System :: Microsoft :: Windows
